{
  "1001": [
    "1539",
    200,
    "silver",
    1
  ],
  "1002": [
    "1285",
    200,
    "silver",
    1
  ],
  "1003": [
    "1541",
    150,
    "silver",
    1
  ],
  "1004": [
    "1281",
    60,
    "gold",
    3
  ],
  "1005": [
    "1282",
    75,
    "gold",
    3
  ],
  "1006": [
    "1283",
    75,
    "gold",
    3
  ],
  "1007": [
    "1284",
    105,
    "gold",
    3
  ],
  "1008": [
    "1285",
    30,
    "gold",
    3
  ],
  "1009": [
    "1540",
    [18,25,35,35,45,45,59],
    "gold",
    1
  ],
  "1010": [
    "silver",
    20,
    "gold",
    350
  ],
  "1011": [
    "silver",
    100,
    "gold",
    2000
  ],
  "1012": [
    "silver",
    200,
    "gold",
    4400
  ],
  "1013": [
    "live",
    18,
    "gold",
    5
  ],
  "1018": [
    0,
    25,
    "gold",
    1
  ]
}